MANIFEST.in
setup.py
flask_routes/__init__.py
flask_routes/router.py
flask_routes/tests/test_router.py
paqmind.flask_routes.egg-info/PKG-INFO
paqmind.flask_routes.egg-info/SOURCES.txt
paqmind.flask_routes.egg-info/dependency_links.txt
paqmind.flask_routes.egg-info/top_level.txt