Metadata-Version: 1.1
Name: paqmind.flask-routes
Version: 0.2.1
Summary: Class-based routes for Flask
Home-page: UNKNOWN
Author: UNKNOWN
Author-email: UNKNOWN
License: MIT
Platform: UNKNOWN
Requires: flask
